CHANGES.txt
COPYRIGHT.txt
LICENSE.txt
README.txt
TODO.txt
ez_setup.py
setup.cfg
setup.py
docs/Makefile
docs/conf.py
docs/index.rst
docs/parser.rst
docs/.static/logo_hi.gif
docs/.static/repoze.css
docs/examples/dv_news.xml
docs/examples/nested.xml
docs/examples/timing.txt
repoze/__init__.py
repoze.urispace.egg-info/PKG-INFO
repoze.urispace.egg-info/SOURCES.txt
repoze.urispace.egg-info/dependency_links.txt
repoze.urispace.egg-info/entry_points.txt
repoze.urispace.egg-info/namespace_packages.txt
repoze.urispace.egg-info/not-zip-safe
repoze.urispace.egg-info/requires.txt
repoze.urispace.egg-info/test_info.txt
repoze.urispace.egg-info/top_level.txt
repoze/urispace/__init__.py
repoze/urispace/interfaces.py
repoze/urispace/middleware.py
repoze/urispace/operators.py
repoze/urispace/parser.py
repoze/urispace/predicates.py
repoze/urispace/selectors.py
repoze/urispace/scripts/__init__.py
repoze/urispace/scripts/uri_test.py
repoze/urispace/tests/__init__.py
repoze/urispace/tests/test_middleware.py
repoze/urispace/tests/test_operators.py
repoze/urispace/tests/test_parser.py
repoze/urispace/tests/test_predicates.py
repoze/urispace/tests/test_selectors.py