Metadata-Version: 1.0
Name: repoze.urispace
Version: 0.3.1
Summary: Library / middleware for URI-based assertions
Home-page: http://www.repoze.org
Author: Agendaless Consulting
Author-email: repoze-dev@lists.repoze.org
License: BSD-derived (http://www.repoze.org/LICENSE.txt)
Keywords: web wsgi zope URISpace
Platform: UNKNOWN
Classifier: Development Status :: 3 - Alpha
Classifier: Intended Audience :: Developers
Classifier: Programming Language :: Python
Classifier: Topic :: Internet :: WWW/HTTP
Classifier: Topic :: Internet :: WWW/HTTP :: Dynamic Content
Classifier: Topic :: Internet :: WWW/HTTP :: WSGI
Classifier: Topic :: Internet :: WWW/HTTP :: WSGI :: Middleware
